rebuilder/__init__.py
rebuilder/auxiliary.py
rebuilder/classes.py
rebuilder/main.py
rebuilder-1.1.data/scripts/rebuilder
rebuilder-1.1.dist-info/LICENSE
rebuilder-1.1.dist-info/METADATA
rebuilder-1.1.dist-info/WHEEL
rebuilder-1.1.dist-info/top_level.txt
rebuilder-1.1.dist-info/RECORD
