Metadata-Version: 2.1
Name: rebuilder
Version: 1.1
Summary: Python program 'rebuilder' constructs PDB models from chain pair interactions.
Home-page: https://github.com/age22/rebuilder
Author: Armand González
Author-email: armandgonzalez01@estudiant.upf.edu
License: UNKNOWN
Platform: UNKNOWN
Requires-Dist: biopython
